LICENSE
MANIFEST.in
README.rst
helga_icanhazascii.py
setup.py
helga_icanhazascii.egg-info/PKG-INFO
helga_icanhazascii.egg-info/SOURCES.txt
helga_icanhazascii.egg-info/dependency_links.txt
helga_icanhazascii.egg-info/entry_points.txt
helga_icanhazascii.egg-info/top_level.txt
helga_icanhazascii.egg-info/zip-safe